clkDivide10w4.sv
module clkDivide10w4
(
    input logic clk,
    input logic rst_n,
    output logic clk10
);

logic [3:0] cnt;
always_ff@(posedge clk or negedge rst_n)begin
    if(!rst_n)
        cnt<=0;
    else if(cnt==9)
        cnt<=0;
    else
        cnt<=cnt+1;
end


always_ff@(posedge clk or negedge rst_n)begin
    if(!rst_n)
        clk10<=0;
    else if(cnt==0 || cnt==1 || cnt==2 || cnt==3)
        clk10<=1;
    else 
        clk10<=0;
end



endmodule

tb_clkDivide10w4.sv
`timescale 1ns/1ps

module tb_clkDivide10w4;

    logic clk;
    logic rst_n;
    logic clk10;

    // Instantiate the Unit Under Test (UUT)
    clkDivide10w4 uut (
        .clk(clk),
        .rst_n(rst_n),
        .clk10(clk10)
    );

    // Clock generation
    initial begin
        clk = 0;
        forever #5 clk = ~clk; // 10ns period -> 100MHz
    end

    // Test sequence
    initial begin
        // Initialize Inputs
        rst_n = 0;

        // Wait 100 ns for global reset to finish
        #100;
        rst_n = 1;

        // Run for a bit
        #1000;
        $finish;
    end

    // Monitor
    initial begin
        $dumpfile("clkDivide10w4.vcd");
        $dumpvars(0, tb_clkDivide10w4);
    end

    real time_rise, period, high_time;
    
    always @(posedge clk10) begin
        if (rst_n) begin
            if (time_rise > 0) begin
                period = $realtime - time_rise;
                if (period != 100.0) $display("Error: Period is %t, expected 100.0", period);
                else $display("Pass: Period is correct: %t", period);
            end
            time_rise = $realtime;
        end
    end

    always @(negedge clk10) begin
        if (rst_n && time_rise > 0) begin
            high_time = $realtime - time_rise;
            if (high_time != 40.0) $display("Error: High time is %t, expected 40.0", high_time);
            else $display("Pass: High time is correct: %t (40%% duty cycle)", high_time);
        end
    end

endmodule

clkDivide10w4.vcd
$date
	Wed Jan 21 11:44:10 2026
$end
$version
	Icarus Verilog
$end
$timescale
	1ps
$end
$scope module tb_clkDivide10w4 $end
$var wire 1 ! clk10 $end
$var reg 1 " clk $end
$var reg 1 # rst_n $end
$var real 1 $ high_time $end
$var real 1 % period $end
$var real 1 & time_rise $end
$scope module uut $end
$var wire 1 " clk $end
$var wire 1 # rst_n $end
$var reg 1 ! clk10 $end
$var reg 4 ' cnt [3:0] $end
$upscope $end
$upscope $end
$enddefinitions $end
#0
$dumpvars
b0 '
r0 &
r0 %
r0 $
0#
0"
0!
$end
#5000
1"
#10000
0"
#15000
1"
#20000
0"
#25000
1"
#30000
0"
#35000
1"
#40000
0"
#45000
1"
#50000
0"
#55000
1"
#60000
0"
#65000
1"
#70000
0"
#75000
1"
#80000
0"
#85000
1"
#90000
0"
#95000
1"
#100000
0"
1#
#105000
r105 &
1!
b1 '
1"
#110000
0"
#115000
b10 '
1"
#120000
0"
#125000
b11 '
1"
#130000
0"
#135000
b100 '
1"
#140000
0"
#145000
r40 $
0!
b101 '
1"
#150000
0"
#155000
b110 '
1"
#160000
0"
#165000
b111 '
1"
#170000
0"
#175000
b1000 '
1"
#180000
0"
#185000
b1001 '
1"
#190000
0"
#195000
b0 '
1"
#200000
0"
#205000
r205 &
r100 %
1!
b1 '
1"
#210000
0"
#215000
b10 '
1"
#220000
0"
#225000
b11 '
1"
#230000
0"
#235000
b100 '
1"
#240000
0"
#245000
0!
b101 '
1"
#250000
0"
#255000
b110 '
1"
#260000
0"
#265000
b111 '
1"
#270000
0"
#275000
b1000 '
1"
#280000
0"
#285000
b1001 '
1"
#290000
0"
#295000
b0 '
1"
#300000
0"
#305000
r305 &
1!
b1 '
1"
#310000
0"
#315000
b10 '
1"
#320000
0"
#325000
b11 '
1"
#330000
0"
#335000
b100 '
1"
#340000
0"
#345000
0!
b101 '
1"
#350000
0"
#355000
b110 '
1"
#360000
0"
#365000
b111 '
1"
#370000
0"
#375000
b1000 '
1"
#380000
0"
#385000
b1001 '
1"
#390000
0"
#395000
b0 '
1"
#400000
0"
#405000
r405 &
1!
b1 '
1"
#410000
0"
#415000
b10 '
1"
#420000
0"
#425000
b11 '
1"
#430000
0"
#435000
b100 '
1"
#440000
0"
#445000
0!
b101 '
1"
#450000
0"
#455000
b110 '
1"
#460000
0"
#465000
b111 '
1"
#470000
0"
#475000
b1000 '
1"
#480000
0"
#485000
b1001 '
1"
#490000
0"
#495000
b0 '
1"
#500000
0"
#505000
r505 &
1!
b1 '
1"
#510000
0"
#515000
b10 '
1"
#520000
0"
#525000
b11 '
1"
#530000
0"
#535000
b100 '
1"
#540000
0"
#545000
0!
b101 '
1"
#550000
0"
#555000
b110 '
1"
#560000
0"
#565000
b111 '
1"
#570000
0"
#575000
b1000 '
1"
#580000
0"
#585000
b1001 '
1"
#590000
0"
#595000
b0 '
1"
#600000
0"
#605000
r605 &
1!
b1 '
1"
#610000
0"
#615000
b10 '
1"
#620000
0"
#625000
b11 '
1"
#630000
0"
#635000
b100 '
1"
#640000
0"
#645000
0!
b101 '
1"
#650000
0"
#655000
b110 '
1"
#660000
0"
#665000
b111 '
1"
#670000
0"
#675000
b1000 '
1"
#680000
0"
#685000
b1001 '
1"
#690000
0"
#695000
b0 '
1"
#700000
0"
#705000
r705 &
1!
b1 '
1"
#710000
0"
#715000
b10 '
1"
#720000
0"
#725000
b11 '
1"
#730000
0"
#735000
b100 '
1"
#740000
0"
#745000
0!
b101 '
1"
#750000
0"
#755000
b110 '
1"
#760000
0"
#765000
b111 '
1"
#770000
0"
#775000
b1000 '
1"
#780000
0"
#785000
b1001 '
1"
#790000
0"
#795000
b0 '
1"
#800000
0"
#805000
r805 &
1!
b1 '
1"
#810000
0"
#815000
b10 '
1"
#820000
0"
#825000
b11 '
1"
#830000
0"
#835000
b100 '
1"
#840000
0"
#845000
0!
b101 '
1"
#850000
0"
#855000
b110 '
1"
#860000
0"
#865000
b111 '
1"
#870000
0"
#875000
b1000 '
1"
#880000
0"
#885000
b1001 '
1"
#890000
0"
#895000
b0 '
1"
#900000
0"
#905000
r905 &
1!
b1 '
1"
#910000
0"
#915000
b10 '
1"
#920000
0"
#925000
b11 '
1"
#930000
0"
#935000
b100 '
1"
#940000
0"
#945000
0!
b101 '
1"
#950000
0"
#955000
b110 '
1"
#960000
0"
#965000
b111 '
1"
#970000
0"
#975000
b1000 '
1"
#980000
0"
#985000
b1001 '
1"
#990000
0"
#995000
b0 '
1"
#1000000
0"
#1005000
r1005 &
1!
b1 '
1"
#1010000
0"
#1015000
b10 '
1"
#1020000
0"
#1025000
b11 '
1"
#1030000
0"
#1035000
b100 '
1"
#1040000
0"
#1045000
0!
b101 '
1"
#1050000
0"
#1055000
b110 '
1"
#1060000
0"
#1065000
b111 '
1"
#1070000
0"
#1075000
b1000 '
1"
#1080000
0"
#1085000
b1001 '
1"
#1090000
0"
#1095000
b0 '
1"
